devvio_util/__init__.py
devvio_util/config.py
devvio_util/decorators.py
devvio_util/lib_creds.py
devvio_util/logging.py
devvio_util/psql_mixin.py
devvio_util/exceptions/__init__.py
devvio_util/exceptions/auth_exceptions.py
devvio_util/exceptions/controller_exceptions.py
devvio_util/exceptions/db_exceptions.py
devvio_util/exceptions/devv_error.py
devvio_util/exceptions/validation_exceptions.py
devvio_util/inn_sdk/__init__.py
devvio_util/inn_sdk/base_client.py
devvio_util/inn_sdk/dfe_client.py
devvio_util/inn_sdk/inn_client.py
devvio_util/inn_sdk/types.py
devvio_util/inn_sdk/utils.py
devvio_util/primitives/__init__.py
devvio_util/primitives/address.py
devvio_util/primitives/atomic_transaction_set.py
devvio_util/primitives/chainstate.py
devvio_util/primitives/devv_constants.py
devvio_util/primitives/devv_sign.py
devvio_util/primitives/final_block.py
devvio_util/primitives/payload.py
devvio_util/primitives/signature.py
devvio_util/primitives/smart_coin.py
devvio_util/primitives/summary.py
devvio_util/primitives/transaction.py
devvio_util/primitives/transfer.py
devvio_util/primitives/utils.py
devvio_util/primitives/validation.py
devvio_util-1.8.7.dist-info/METADATA
devvio_util-1.8.7.dist-info/WHEEL
devvio_util-1.8.7.dist-info/top_level.txt
devvio_util-1.8.7.dist-info/RECORD
