Metadata-Version: 2.4
Name: devvio_util
Version: 1.8.7
Summary: Utility to be used inside Devvio projects
Author: Devvio Team
Author-email: support@devv.io
License: Devvio
Classifier: Programming Language :: Python :: 3
Classifier: License :: OSI Approved :: MIT License
Classifier: Operating System :: OS Independent
Requires-Dist: flake8==6.0.0
Requires-Dist: cryptography==41.0.1
Dynamic: author
Dynamic: author-email
Dynamic: classifier
Dynamic: description-content-type
Dynamic: license
Dynamic: requires-dist
Dynamic: summary
